Metadata-Version: 2.1
Name: odoo10-addon-hr-holidays-notify-employee-manager
Version: 10.0.1.0.0.99.dev7
Summary: Notify employee's manager by mail on Leave Requests creation.
Home-page: https://github.com/OCA/hr
Author: Eficent, Odoo Community Association (OCA)
Author-email: support@odoo-community.org
License: AGPL-3
Platform: UNKNOWN
Classifier: Programming Language :: Python
Classifier: Framework :: Odoo
Classifier: Framework :: Odoo :: 10.0
Classifier: License :: OSI Approved :: GNU Affero General Public License v3
Requires-Python: ~=2.7
Requires-Dist: odoo10-addon-hr-holidays-settings
Requires-Dist: odoo <10.1dev,>=10.0
